azure/mgmt/purestorageblock/__init__.py
azure/mgmt/purestorageblock/_client.py
azure/mgmt/purestorageblock/_configuration.py
azure/mgmt/purestorageblock/_patch.py
azure/mgmt/purestorageblock/_validation.py
azure/mgmt/purestorageblock/_version.py
azure/mgmt/purestorageblock/py.typed
azure/mgmt/purestorageblock/_utils/__init__.py
azure/mgmt/purestorageblock/_utils/model_base.py
azure/mgmt/purestorageblock/_utils/serialization.py
azure/mgmt/purestorageblock/aio/__init__.py
azure/mgmt/purestorageblock/aio/_client.py
azure/mgmt/purestorageblock/aio/_configuration.py
azure/mgmt/purestorageblock/aio/_patch.py
azure/mgmt/purestorageblock/aio/operations/__init__.py
azure/mgmt/purestorageblock/aio/operations/_operations.py
azure/mgmt/purestorageblock/aio/operations/_patch.py
azure/mgmt/purestorageblock/models/__init__.py
azure/mgmt/purestorageblock/models/_enums.py
azure/mgmt/purestorageblock/models/_models.py
azure/mgmt/purestorageblock/models/_patch.py
azure/mgmt/purestorageblock/operations/__init__.py
azure/mgmt/purestorageblock/operations/_operations.py
azure/mgmt/purestorageblock/operations/_patch.py
azure_mgmt_purestorageblock-1.0.0.dist-info/LICENSE
azure_mgmt_purestorageblock-1.0.0.dist-info/METADATA
azure_mgmt_purestorageblock-1.0.0.dist-info/WHEEL
azure_mgmt_purestorageblock-1.0.0.dist-info/top_level.txt
azure_mgmt_purestorageblock-1.0.0.dist-info/RECORD
